newsspider/__init__.py
newsspider/items.py
newsspider/pipelines.py
newsspider/settings.py
newsspider/spiders/__init__.py
newsspider/spiders/news_spider.py
wba_news_spider_scrapy-1.0.dist-info/METADATA
wba_news_spider_scrapy-1.0.dist-info/WHEEL
wba_news_spider_scrapy-1.0.dist-info/entry_points.txt
wba_news_spider_scrapy-1.0.dist-info/top_level.txt
wba_news_spider_scrapy-1.0.dist-info/RECORD
