Metadata-Version: 2.1
Name: wba-news-spider-scrapy
Version: 1.0
Summary: A web scraping tool using Scrapy to gather news data.
Author: Michel Padron
Author-email: michel@padmora.com
